gluesql-0.18.0.dist-info/METADATA
gluesql-0.18.0.dist-info/WHEEL
gluesql/__init__.py
gluesql/__init__.pyi
gluesql/gluesql.cpython-311-darwin.so
gluesql/py.typed
gluesql-0.18.0.dist-info/RECORD
