Metadata-Version: 2.4
Name: gluesql
Version: 0.18.0
Classifier: Programming Language :: Rust
Classifier: Programming Language :: Python :: Implementation :: CPython
Summary: GlueSQL is quite sticky. It attaches to anywhere.
Requires-Python: >=3.10
